[
    {
        "id":"1", 
        "job":"squire", 
        "type":"Non-Magic", 
        "image":"https://vignette2.wikia.nocookie.net/finalfantasy/images/5/51/Squires.jpg/revision/latest?cb=20090401223303"
    },
    {
        "id":"2", 
        "job":"knight", 
        "type":"Non-Magic", 
        "image":"http://www.gamer.ru/system/attached_images/images/000/117/508/original/knights.jpg"
    }, 
    
    {
        "id":"3", 
        "job":"Archer", 
        "type":"Non-Magic", 
        "image":"https://vignette4.wikia.nocookie.net/finalfantasy/images/7/7d/FFT_Archer.jpg/revision/latest?cb=20070228173549"
    }, 
    {
        "id":"4", 
        "job":"Monk", 
        "type":"Non-Magic", 
        "image":"https://vignette1.wikia.nocookie.net/finalfantasy/images/d/d3/FFT_Monk.jpg/revision/latest?cb=20090402230052"
    }, 
    {
        "id":"5", 
        "job":"Thief", 
        "type":"Non-Magic", 
        "image":"https://vignette2.wikia.nocookie.net/finalfantasy/images/2/20/FFT_Thief.jpg/revision/latest?cb=20090402231758"
    }, 
    {
        "id":"6", 
        "job":"Geomancer", 
        "type":"Non-Magic", 
        "image":"http://vignette4.wikia.nocookie.net/finalfantasy/images/7/7c/FFT_Geomancer.jpg/revision/latest?cb=20090402235257"
    }, 
    {
        "id":"7", 
        "job":"Lancer", 
        "type":"Non-Magic", 
        "image":"https://vignette3.wikia.nocookie.net/finalfantasy/images/1/19/Lancer.jpg/revision/latest?cb=20090403104918"
    }, 
    {
        "id":"8", 
        "job":"Samurai", 
        "type":"Non-Magic", 
        "image":"https://vignette4.wikia.nocookie.net/finalfantasy/images/a/a8/FFT_Samurai.jpg/revision/latest?cb=20090403110430"
    }, 
    {
        "id":"9", 
        "job":"Ninja", 
        "type":"Non-Magic", 
        "image":"https://vignette2.wikia.nocookie.net/finalfantasy/images/9/97/FFT_Ninja.jpg/revision/latest?cb=20090403231129"
    }, 
    {
        "id":"10", 
        "job":"Dancer", 
        "type":"Non-Magic", 
        "image":"https://vignette3.wikia.nocookie.net/finalfantasy/images/8/8a/Dancer.jpg/revision/latest/scale-to-width-down/294?cb=20080225083047"
    }, 
    {
        "id":"11", 
        "job":"Chemist", 
        "type":"Magic", 
        "image":"https://vignette2.wikia.nocookie.net/finalfantasy/images/a/ae/FFT_Chemist.jpg/revision/latest?cb=20090404120246"
    }, 
    {
        "id":"12", 
        "job":"White Mage",
        "type":"Magic", 
        "image":"https://vignette2.wikia.nocookie.net/finalfantasy/images/b/b6/Priest.jpg/revision/latest?cb=20090404122508"
    }, 
    {
        "id":"13", 
        "job":"Black Mage", 
        "type":"Magic", 
        "image":"https://vignette4.wikia.nocookie.net/finalfantasy/images/7/78/Wizardfft.jpg/revision/latest?cb=20090404124236"
    }, 
    {
        "id":"14", 
        "job":"Mystic", 
        "type":"Magic", 
        "image":"https://s-media-cache-ak0.pinimg.com/originals/ce/de/6a/cede6aeaae730d0d8fbd31dc5beee117.png"
    }, 
    {
        "id":"15", 
        "job":"Timemage",
        "type":"Magic", 
        "image":"https://vignette1.wikia.nocookie.net/finalfantasy/images/b/b6/FFT_Time_mage.jpg/revision/latest?cb=20090404230237"
    }, 
    {
        "id":"16", 
        "job":"Orator", 
        "type":"Magic", 
        "image":"https://vignette4.wikia.nocookie.net/finalfantasy/images/e/ec/FFT_Mediator.jpg/revision/latest?cb=20090405010014"
    }, 
    {
        "id":"17",
        "job":"Summoner", 
        "type":"Magic", 
        "image":"https://vignette2.wikia.nocookie.net/finalfantasy/images/e/ec/FFT_Summoner.jpg/revision/latest?cb=20090405133912"
    }, 
    {
        "id":"18", 
        "job":"Bard", 
        "type":"Magic", 
        "image":"https://vignette3.wikia.nocookie.net/finalfantasy/images/f/fe/FFT_Bard.jpg/revision/latest/scale-to-width-down/229?cb=20111202173530"
    }, 
    {
        "id":"19", 
        "job":"Calculator", 
        "type":"Magic", 
        "image":"https://vignette1.wikia.nocookie.net/finalfantasy/images/7/77/Calculator.jpg/revision/latest?cb=20090405145306"
    }, 
    {
        "id":"20", 
        "job":"Mime", 
        "type":"Magic", 
        "image":"http://vignette3.wikia.nocookie.net/finalfantasy/images/6/6b/FFTacticsMime.jpg/revision/latest?cb=20090405192720"
    }, 
    {
        "id":"21", 
        "job":"Holy Knight", 
        "type":"Special", 
        "image":"https://vignette4.wikia.nocookie.net/finalfantasy/images/7/7e/Agrias.jpg/revision/latest?cb=20100705234845"
    }, 
    {
        "id":"22", 
        "job":"Dark Knight", 
        "type":"Special", 
        "image":"http://vignette1.wikia.nocookie.net/finalfantasy/images/c/c7/FFT_DarkKnight.jpg/revision/latest?cb=20070420194940"
    }, 
    {
        "id":"23", 
        "job":"Cleric", 
        "type":"Special", 
        "image":"https://vignette2.wikia.nocookie.net/finalfantasy/images/3/3b/Fft-alma-beoulve.jpg/revision/latest/scale-to-width-down/260?cb=20161006233123"
    }, 
    {
        "id":"24", 
        "job":"Engineer", 
        "type":"Special", 
        "image":"https://vignette2.wikia.nocookie.net/finalfantasy/images/e/e3/Mustadio.jpg/revision/latest?cb=20100705233134"
    }, 
    {
        "id":"25", 
        "job":"Astrologist", 
        "type":"Special", 
        "image":"https://vignette3.wikia.nocookie.net/finalfantasy/images/7/71/Olan.jpg/revision/latest?cb=20100705235113"
    }, 
    {
        "id":"26", 
        "job":"Divine Knight",
        "type":"Special", 
        "image":"http://static.zerochan.net/Meliadoul.Tengille.full.125057.jpg"
    }, 
    {
        "id":"27", 
        "job":"Sword Saint", 
        "type":"Special", 
        "image":"https://vignette2.wikia.nocookie.net/finalfantasy/images/1/15/Orlandu.jpg/revision/latest?cb=20100705234956"
    }, 
    {
        "id":"28", 
        "job":"Arc Knight", 
        "type":"Special", 
        "image":"https://vignette4.wikia.nocookie.net/finalfantasy/images/9/9c/Fft-zalbaag-beoulve.jpg/revision/latest/scale-to-width-down/350?cb=20080203052939"
    }, 
    {
        "id":"29", 
        "job":"Assassin", 
        "type":"Special", 
        "image":"https://i.pinimg.com/736x/0e/74/65/0e7465542b35fa93382407f32a7a3a30--character-concept-character-art.jpg"
    }, 
    {
        "id":"30", 
        "job":"Temple Knight", 
        "type":"Special", 
        "image":"http://vignette3.wikia.nocookie.net/finalfantasy/images/4/4f/Fft-dycedarg-beoulve.jpg/revision/latest?cb=20080203052805"
    }, 
    {
        "id":"31", 
        "job":"Dragonkin", 
        "type":"Special", 
        "image":"https://vignette4.wikia.nocookie.net/final-fantasy-tactics-the-war-of-the-lions/images/5/55/FFT_Bahamut.jpg/revision/latest?cb=20150714143655"
    }, 
    {
        "id":"32", 
        "job":"Soldier", 
        "type":"Special", 
        "image":"https://static.comicvine.com/uploads/original/2/28028/738142-cloud.jpg"
    }]